named_bitfield.py
setup.py
named_bitfield.egg-info/PKG-INFO
named_bitfield.egg-info/SOURCES.txt
named_bitfield.egg-info/dependency_links.txt
named_bitfield.egg-info/requires.txt
named_bitfield.egg-info/top_level.txt