Metadata-Version: 1.1
Name: named-bitfield
Version: 0.1.0
Summary: Compact representation of fixed width numeric values
Home-page: https://github.com/not-napoleon/named_bitfield
Author: Mark Tozzi
Author-email: mark.tozzi+pypi@gmail.com
License: MIT
Keywords: bitfields bitstrings smart_ids
Platform: UNKNOWN
Classifier: Development Status :: 4 - Beta
Classifier: Intended Audience :: Developers
Classifier: Topic :: Utilities
Classifier: License :: OSI Approved :: MIT License
Classifier: Programming Language :: Python :: 2.7
Classifier: Programming Language :: Python :: 3.4
